{
 "Description": "Academia Frontend - staging",
 "Resources": {
  "FrontendBucketEFE2E19C": {
   "Type": "AWS::S3::Bucket",
   "Properties": {
    "BucketEncryption": {
     "ServerSideEncryptionConfiguration": [
      {
       "ServerSideEncryptionByDefault": {
        "SSEAlgorithm": "AES256"
       }
      }
     ]
    },
    "BucketName": "academia-frontend-staging-771643347382",
    "PublicAccessBlockConfiguration": {
     "BlockPublicAcls": true,
     "BlockPublicPolicy": true,
     "IgnorePublicAcls": true,
     "RestrictPublicBuckets": true
    },
    "VersioningConfiguration": {
     "Status": "Enabled"
    }
   },
   "UpdateReplacePolicy": "Delete",
   "DeletionPolicy": "Delete",
   "Metadata": {
    "aws:cdk:path": "AcademiaFrontend-Staging/FrontendBucket/Resource"
   }
  },
  "FrontendBucketPolicy1DFF75D9": {
   "Type": "AWS::S3::BucketPolicy",
   "Properties": {
    "Bucket": {
     "Ref": "FrontendBucketEFE2E19C"
    },
    "PolicyDocument": {
     "Statement": [
      {
       "Action": [
        "s3:GetObject*",
        "s3:GetBucket*",
        "s3:List*"
       ],
       "Effect": "Allow",
       "Principal": {
        "CanonicalUser": {
         "Fn::GetAtt": [
          "OAIE1EFC67F",
          "S3CanonicalUserId"
         ]
        }
       },
       "Resource": [
        {
         "Fn::GetAtt": [
          "FrontendBucketEFE2E19C",
          "Arn"
         ]
        },
        {
         "Fn::Join": [
          "",
          [
           {
            "Fn::GetAtt": [
             "FrontendBucketEFE2E19C",
             "Arn"
            ]
           },
           "/*"
          ]
         ]
        }
       ]
      },
      {
       "Action": "s3:GetObject",
       "Effect": "Allow",
       "Principal": {
        "CanonicalUser": {
         "Fn::GetAtt": [
          "OAIE1EFC67F",
          "S3CanonicalUserId"
         ]
        }
       },
       "Resource": {
        "Fn::Join": [
         "",
         [
          {
           "Fn::GetAtt": [
            "FrontendBucketEFE2E19C",
            "Arn"
           ]
          },
          "/*"
         ]
        ]
       }
      }
     ],
     "Version": "2012-10-17"
    }
   },
   "Metadata": {
    "aws:cdk:path": "AcademiaFrontend-Staging/FrontendBucket/Policy/Resource"
   }
  },
  "OAIE1EFC67F": {
   "Type": "AWS::CloudFront::CloudFrontOriginAccessIdentity",
   "Properties": {
    "CloudFrontOriginAccessIdentityConfig": {
     "Comment": "Academia Frontend OAI"
    }
   },
   "Metadata": {
    "aws:cdk:path": "AcademiaFrontend-Staging/OAI/Resource"
   }
  },
  "Distribution830FAC52": {
   "Type": "AWS::CloudFront::Distribution",
   "Properties": {
    "DistributionConfig": {
     "CacheBehaviors": [
      {
       "AllowedMethods": [
        "GET",
        "HEAD",
        "OPTIONS",
        "PUT",
        "PATCH",
        "POST",
        "DELETE"
       ],
       "CachePolicyId": "4135ea2d-6df8-44a3-9df3-4b5a84be39ad",
       "Compress": true,
       "OriginRequestPolicyId": "b689b0a8-53d0-40ab-baf2-68738e2966ac",
       "PathPattern": "/api/*",
       "TargetOriginId": "AcademiaFrontendStagingDistributionOrigin25FA27BBC",
       "ViewerProtocolPolicy": "https-only"
      },
      {
       "AllowedMethods": [
        "GET",
        "HEAD",
        "OPTIONS",
        "PUT",
        "PATCH",
        "POST",
        "DELETE"
       ],
       "CachePolicyId": "4135ea2d-6df8-44a3-9df3-4b5a84be39ad",
       "Compress": true,
       "OriginRequestPolicyId": "b689b0a8-53d0-40ab-baf2-68738e2966ac",
       "PathPattern": "/graphql",
       "TargetOriginId": "AcademiaFrontendStagingDistributionOrigin3A7E70AF6",
       "ViewerProtocolPolicy": "https-only"
      }
     ],
     "CustomErrorResponses": [
      {
       "ErrorCachingMinTTL": 300,
       "ErrorCode": 403,
       "ResponseCode": 200,
       "ResponsePagePath": "/index.html"
      },
      {
       "ErrorCachingMinTTL": 300,
       "ErrorCode": 404,
       "ResponseCode": 200,
       "ResponsePagePath": "/index.html"
      }
     ],
     "DefaultCacheBehavior": {
      "AllowedMethods": [
       "GET",
       "HEAD",
       "OPTIONS"
      ],
      "CachePolicyId": "658327ea-f89d-4fab-a63d-7e88639e58f6",
      "Compress": true,
      "TargetOriginId": "AcademiaFrontendStagingDistributionOrigin14B001D10",
      "ViewerProtocolPolicy": "redirect-to-https"
     },
     "DefaultRootObject": "index.html",
     "Enabled": true,
     "HttpVersion": "http2",
     "IPV6Enabled": true,
     "Origins": [
      {
       "DomainName": {
        "Fn::GetAtt": [
         "FrontendBucketEFE2E19C",
         "RegionalDomainName"
        ]
       },
       "Id": "AcademiaFrontendStagingDistributionOrigin14B001D10",
       "S3OriginConfig": {
        "OriginAccessIdentity": {
         "Fn::Join": [
          "",
          [
           "origin-access-identity/cloudfront/",
           {
            "Ref": "OAIE1EFC67F"
           }
          ]
         ]
        }
       }
      },
      {
       "CustomOriginConfig": {
        "OriginProtocolPolicy": "https-only",
        "OriginSSLProtocols": [
         "TLSv1.2"
        ]
       },
       "DomainName": {
        "Fn::Join": [
         "",
         [
          {
           "Fn::ImportValue": "AcademiaBackend-Staging:ExportsOutputRefAcademiaApiEB0FBB3526983528"
          },
          ".execute-api.us-east-1.",
          {
           "Ref": "AWS::URLSuffix"
          }
         ]
        ]
       },
       "Id": "AcademiaFrontendStagingDistributionOrigin25FA27BBC",
       "OriginPath": "/prod"
      },
      {
       "CustomOriginConfig": {
        "OriginProtocolPolicy": "https-only",
        "OriginSSLProtocols": [
         "TLSv1.2"
        ]
       },
       "DomainName": {
        "Fn::Join": [
         "",
         [
          {
           "Fn::ImportValue": "AcademiaBackend-Staging:ExportsOutputRefAcademiaApiEB0FBB3526983528"
          },
          ".execute-api.us-east-1.",
          {
           "Ref": "AWS::URLSuffix"
          }
         ]
        ]
       },
       "Id": "AcademiaFrontendStagingDistributionOrigin3A7E70AF6",
       "OriginPath": "/prod"
      }
     ],
     "PriceClass": "PriceClass_100"
    }
   },
   "Metadata": {
    "aws:cdk:path": "AcademiaFrontend-Staging/Distribution/Resource"
   }
  },
  "CDKMetadata": {
   "Type": "AWS::CDK::Metadata",
   "Properties": {
    "Analytics": "v2:deflate64:H4sIAAAAAAAA/22LwQrCMBBEv6X3dK0peNeK4KmiHyBtksramkh2Y5GSf5dYQQ+eZubxRoIsSyiyZqRc6T4fsIXpxI3qRTPSeaISpk1QvWFRdfbT5ji4AdXzi+cdhRpc0J13lmGqPV7QrpUyRHttLCO/H1Vydsn5a2yR2GMbGJ1N+u+OMZE68D1wFNZpA1daPKSE5QqK7EqIuQ+W8WbgOOcLz29CA+UAAAA="
   },
   "Metadata": {
    "aws:cdk:path": "AcademiaFrontend-Staging/CDKMetadata/Default"
   }
  }
 },
 "Outputs": {
  "FrontendUrl": {
   "Description": "Frontend URL",
   "Value": {
    "Fn::Join": [
     "",
     [
      "https://",
      {
       "Fn::GetAtt": [
        "Distribution830FAC52",
        "DomainName"
       ]
      }
     ]
    ]
   },
   "Export": {
    "Name": "academia-staging-frontend-url"
   }
  },
  "DistributionId": {
   "Description": "CloudFront Distribution ID",
   "Value": {
    "Ref": "Distribution830FAC52"
   },
   "Export": {
    "Name": "academia-staging-distribution-id"
   }
  },
  "DistributionDomainName": {
   "Description": "CloudFront Distribution Domain Name",
   "Value": {
    "Fn::GetAtt": [
     "Distribution830FAC52",
     "DomainName"
    ]
   }
  },
  "FrontendBucketName": {
   "Description": "Frontend S3 Bucket",
   "Value": {
    "Ref": "FrontendBucketEFE2E19C"
   },
   "Export": {
    "Name": "academia-staging-frontend-bucket"
   }
  }
 },
 "Parameters": {
  "BootstrapVersion": {
   "Type": "AWS::SSM::Parameter::Value<String>",
   "Default": "/cdk-bootstrap/hnb659fds/version",
   "Description": "Version of the CDK Bootstrap resources in this environment, automatically retrieved from SSM Parameter Store. [cdk:skip]"
  }
 },
 "Rules": {
  "CheckBootstrapVersion": {
   "Assertions": [
    {
     "Assert": {
      "Fn::Not": [
       {
        "Fn::Contains": [
         [
          "1",
          "2",
          "3",
          "4",
          "5"
         ],
         {
          "Ref": "BootstrapVersion"
         }
        ]
       }
      ]
     },
     "AssertDescription": "CDK bootstrap stack version 6 required. Please run 'cdk bootstrap' with a recent version of the CDK CLI."
    }
   ]
  }
 }
}